{
  "road_regions": [
    {
      "center_x": -5.138401031494141,
      "center_y": 0.5129127502441406,
      "center_z": 0.0,
      "size_x": 49.34257125854492,
      "size_y": 13.577136993408203,
      "size_z": 4.0,
      "rot_z": 0.0
    },
    {
      "center_x": -6.425165176391602,
      "center_y": 13.690669059753418,
      "center_z": 0.0,
      "size_x": 46.3693962097168,
      "size_y": 14.336465835571289,
      "size_z": 4.0,
      "rot_z": 0.0
    },
    {
      "center_x": 0.07245969772338867,
      "center_y": 20.84743881225586,
      "center_z": 0.0,
      "size_x": 31.66619873046875,
      "size_y": 5.056894302368164,
      "size_z": 4.0,
      "rot_z": 0.0
    }
  ],
  "background_regions": [
    {
      "center_x": 0.0,
      "center_y": 0.0,
      "center_z": 0.0,
      "size_x": 4.0,
      "size_y": 2.0,
      "size_z": 2.0,
      "rot_z": 0.0
    },
    {
      "center_x": -13.413236618041992,
      "center_y": 7.939461708068848,
      "center_z": 0.0,
      "size_x": 30.35158920288086,
      "size_y": 3.2481460571289062,
      "size_z": 4.0,
      "rot_z": 0.0
    },
    {
      "center_x": 1.249460220336914,
      "center_y": -3.8577957153320312,
      "center_z": 0.0,
      "size_x": 1.4595308303833008,
      "size_y": 1.6275522708892822,
      "size_z": 4.0,
      "rot_z": 0.0
    },
    {
      "center_x": -6.702959060668945,
      "center_y": -3.054328203201294,
      "center_z": 0.0,
      "size_x": 16.802085876464844,
      "size_y": 0.9926533699035645,
      "size_z": 4.0,
      "rot_z": 0.0
    },
    {
      "center_x": -0.04329286515712738,
      "center_y": -4.699227333068848,
      "center_z": 0.0,
      "size_x": 0.3556962311267853,
      "size_y": 0.3478527069091797,
      "size_z": 4.0,
      "rot_z": 0.0
    },
    {
      "center_x": -5.473252296447754,
      "center_y": 20.756938934326172,
      "center_z": 0.0,
      "size_x": 0.7415165901184082,
      "size_y": 0.7615566253662109,
      "size_z": 4.0,
      "rot_z": 0.0
    },
    {
      "center_x": -28.37423324584961,
      "center_y": -3.8279271125793457,
      "center_z": 0.0,
      "size_x": 1.3096771240234375,
      "size_y": 1.302750587463379,
      "size_z": 4.0,
      "rot_z": 0.0
    }
  ]
}
