{
  "road_regions": [
    {
      "center_x": 0.08695831298828138,
      "center_y": 0.8427827835083004,
      "center_z": 0.0,
      "size_x": 34.49971008300781,
      "size_y": 14.575927734375,
      "size_z": 4.0,
      "rot_z": -0.030000000000000006
    },
    {
      "center_x": 15.074910163879395,
      "center_y": 3.4815268516540527,
      "center_z": 0.0,
      "size_x": 10.110799789428711,
      "size_y": 32.98044967651367,
      "size_z": 4.0,
      "rot_z": 0.0
    }
  ],
  "background_regions": [
    {
      "center_x": 0.0,
      "center_y": 0.0,
      "center_z": 0.0,
      "size_x": 4.0,
      "size_y": 2.0,
      "size_z": 2.0,
      "rot_z": 0.0
    },
    {
      "center_x": -11.148618698120117,
      "center_y": 7.270593643188477,
      "center_z": 0.0,
      "size_x": 0.8669166564941406,
      "size_y": 1.1078076362609863,
      "size_z": 4.0,
      "rot_z": 0.0
    },
    {
      "center_x": -13.708465576171875,
      "center_y": 7.3141374588012695,
      "center_z": 0.0,
      "size_x": 1.5009746551513672,
      "size_y": 1.7054767608642578,
      "size_z": 4.0,
      "rot_z": 0.0
    },
    {
      "center_x": 9.463671684265137,
      "center_y": 7.656015396118164,
      "center_z": 0.0,
      "size_x": 1.2038898468017578,
      "size_y": 0.7586135864257812,
      "size_z": 4.0,
      "rot_z": 0.0
    },
    {
      "center_x": 5.20139217376709,
      "center_y": 6.134555816650391,
      "center_z": 0.0,
      "size_x": 1.4579081535339355,
      "size_y": 0.9988498687744141,
      "size_z": 4.0,
      "rot_z": 0.0
    },
    {
      "center_x": 10.560346603393555,
      "center_y": 13.992475509643555,
      "center_z": 0.0,
      "size_x": 1.0096120834350586,
      "size_y": 1.015629768371582,
      "size_z": 4.0,
      "rot_z": 0.0
    }
  ]
}
